README.rst
setup.py
wtforms_jsonschema/__init__.py
wtforms_jsonschema/jsonschema.py
wtforms_jsonschema.egg-info/PKG-INFO
wtforms_jsonschema.egg-info/SOURCES.txt
wtforms_jsonschema.egg-info/dependency_links.txt
wtforms_jsonschema.egg-info/not-zip-safe
wtforms_jsonschema.egg-info/top_level.txt