Metadata-Version: 1.1
Name: wtforms-jsonschema
Version: 0.0.6
Summary: wtforms-jsonschema converts WTForms into JSON Schema compatibile representations
Home-page: http://github.com/zbyte64/wtforms-jsonschema
Author: Jason Kraus
Author-email: zbyte64@gmail.com
License: New BSD License
Keywords: wtforms json schema
Platform: UNKNOWN
Classifier: Programming Language :: Python
Classifier: Environment :: Web Environment
Classifier: Operating System :: OS Independent
Classifier: Natural Language :: English
Classifier: Development Status :: 4 - Beta
Classifier: Intended Audience :: Developers
Classifier: License :: OSI Approved :: BSD License
Classifier: Topic :: Internet :: WWW/HTTP :: Dynamic Content
